exec_mcp_server/__init__.py
exec_mcp_server/__main__.py
exec_mcp_server/server.py
exec_mcp_server-0.4.0.dist-info/METADATA
exec_mcp_server-0.4.0.dist-info/WHEEL
exec_mcp_server-0.4.0.dist-info/entry_points.txt
exec_mcp_server-0.4.0.dist-info/top_level.txt
exec_mcp_server-0.4.0.dist-info/RECORD
