Metadata-Version: 2.4
Name: exec_mcp_server
Version: 0.4.0
Summary: 命令执行
Requires-Python: >=3.10
Requires-Dist: httpx>=0.28.1
Requires-Dist: mcp>=1.11.0
